{
	"configurations" : 
	[
		{
			"directories" : 
			[
				{
					"build" : ".",
					"childIndexes" : 
					[
						1
					],
					"hasInstallRule" : true,
					"jsonFile" : "directory-.-Debug-d0094a50bb2071803777.json",
					"minimumCMakeVersion" : 
					{
						"string" : "3.10"
					},
					"projectIndex" : 0,
					"source" : ".",
					"targetIndexes" : 
					[
						0,
						1,
						4
					]
				},
				{
					"build" : "raylib",
					"childIndexes" : 
					[
						2
					],
					"hasInstallRule" : true,
					"jsonFile" : "directory-raylib-Debug-dac977eb2014d01c94e9.json",
					"minimumCMakeVersion" : 
					{
						"string" : "3.25"
					},
					"parentIndex" : 0,
					"projectIndex" : 1,
					"source" : "raylib",
					"targetIndexes" : 
					[
						2
					]
				},
				{
					"build" : "raylib/raylib",
					"childIndexes" : 
					[
						3
					],
					"hasInstallRule" : true,
					"jsonFile" : "directory-raylib.raylib-Debug-8445f1a9fc5e146d2841.json",
					"minimumCMakeVersion" : 
					{
						"string" : "3.25"
					},
					"parentIndex" : 1,
					"projectIndex" : 1,
					"source" : "raylib/src",
					"targetIndexes" : 
					[
						6
					]
				},
				{
					"build" : "raylib/raylib/external/glfw",
					"childIndexes" : 
					[
						4
					],
					"jsonFile" : "directory-raylib.raylib.external.glfw-Debug-38845233cd217b380713.json",
					"minimumCMakeVersion" : 
					{
						"string" : "3.4"
					},
					"parentIndex" : 2,
					"projectIndex" : 2,
					"source" : "raylib/src/external/glfw",
					"targetIndexes" : 
					[
						3
					]
				},
				{
					"build" : "raylib/raylib/external/glfw/src",
					"jsonFile" : "directory-raylib.raylib.external.glfw.src-Debug-4d55a53c058fdfa6d7b4.json",
					"minimumCMakeVersion" : 
					{
						"string" : "3.4"
					},
					"parentIndex" : 3,
					"projectIndex" : 2,
					"source" : "raylib/src/external/glfw/src",
					"targetIndexes" : 
					[
						5,
						7
					]
				}
			],
			"name" : "Debug",
			"projects" : 
			[
				{
					"childIndexes" : 
					[
						1
					],
					"directoryIndexes" : 
					[
						0
					],
					"name" : "4MB_Game_Jam",
					"targetIndexes" : 
					[
						0,
						1,
						4
					]
				},
				{
					"childIndexes" : 
					[
						2
					],
					"directoryIndexes" : 
					[
						1,
						2
					],
					"name" : "raylib",
					"parentIndex" : 0,
					"targetIndexes" : 
					[
						2,
						6
					]
				},
				{
					"directoryIndexes" : 
					[
						3,
						4
					],
					"name" : "GLFW",
					"parentIndex" : 1,
					"targetIndexes" : 
					[
						3,
						5,
						7
					]
				}
			],
			"targets" : 
			[
				{
					"directoryIndex" : 0,
					"id" : "4MB_Game_Jam::@6890427a1f51a3e7e1df",
					"jsonFile" : "target-4MB_Game_Jam-Debug-7c96c76f6a30f5e83041.json",
					"name" : "4MB_Game_Jam",
					"projectIndex" : 0
				},
				{
					"directoryIndex" : 0,
					"id" : "ALL_BUILD::@6890427a1f51a3e7e1df",
					"jsonFile" : "target-ALL_BUILD-Debug-2bcba8660bbe64b53a9c.json",
					"name" : "ALL_BUILD",
					"projectIndex" : 0
				},
				{
					"directoryIndex" : 1,
					"id" : "ALL_BUILD::@5003b8f497eeabc0006e",
					"jsonFile" : "target-ALL_BUILD-Debug-c559b9ce9e9198be3419.json",
					"name" : "ALL_BUILD",
					"projectIndex" : 1
				},
				{
					"directoryIndex" : 3,
					"id" : "ALL_BUILD::@9b50ec0f4b893e94b571",
					"jsonFile" : "target-ALL_BUILD-Debug-c98b6fdae7bb02c24a13.json",
					"name" : "ALL_BUILD",
					"projectIndex" : 2
				},
				{
					"directoryIndex" : 0,
					"id" : "ZERO_CHECK::@6890427a1f51a3e7e1df",
					"jsonFile" : "target-ZERO_CHECK-Debug-85400f93d8e2ec8710c8.json",
					"name" : "ZERO_CHECK",
					"projectIndex" : 0
				},
				{
					"directoryIndex" : 4,
					"id" : "glfw::@a896dd99b4a5c6eab3d9",
					"jsonFile" : "target-glfw-Debug-9e95a3f563948a507623.json",
					"name" : "glfw",
					"projectIndex" : 2
				},
				{
					"directoryIndex" : 2,
					"id" : "raylib::@7d429ebd5d102775094d",
					"jsonFile" : "target-raylib-Debug-ca98ff3bd7becb6adc3a.json",
					"name" : "raylib",
					"projectIndex" : 1
				},
				{
					"directoryIndex" : 4,
					"id" : "update_mappings::@a896dd99b4a5c6eab3d9",
					"jsonFile" : "target-update_mappings-Debug-b78b28e94bedbf65146e.json",
					"name" : "update_mappings",
					"projectIndex" : 2
				}
			]
		},
		{
			"directories" : 
			[
				{
					"build" : ".",
					"childIndexes" : 
					[
						1
					],
					"hasInstallRule" : true,
					"jsonFile" : "directory-.-Release-d0094a50bb2071803777.json",
					"minimumCMakeVersion" : 
					{
						"string" : "3.10"
					},
					"projectIndex" : 0,
					"source" : ".",
					"targetIndexes" : 
					[
						0,
						1,
						4
					]
				},
				{
					"build" : "raylib",
					"childIndexes" : 
					[
						2
					],
					"hasInstallRule" : true,
					"jsonFile" : "directory-raylib-Release-dac977eb2014d01c94e9.json",
					"minimumCMakeVersion" : 
					{
						"string" : "3.25"
					},
					"parentIndex" : 0,
					"projectIndex" : 1,
					"source" : "raylib",
					"targetIndexes" : 
					[
						2
					]
				},
				{
					"build" : "raylib/raylib",
					"childIndexes" : 
					[
						3
					],
					"hasInstallRule" : true,
					"jsonFile" : "directory-raylib.raylib-Release-246923017d3e3b46df60.json",
					"minimumCMakeVersion" : 
					{
						"string" : "3.25"
					},
					"parentIndex" : 1,
					"projectIndex" : 1,
					"source" : "raylib/src",
					"targetIndexes" : 
					[
						6
					]
				},
				{
					"build" : "raylib/raylib/external/glfw",
					"childIndexes" : 
					[
						4
					],
					"jsonFile" : "directory-raylib.raylib.external.glfw-Release-38845233cd217b380713.json",
					"minimumCMakeVersion" : 
					{
						"string" : "3.4"
					},
					"parentIndex" : 2,
					"projectIndex" : 2,
					"source" : "raylib/src/external/glfw",
					"targetIndexes" : 
					[
						3
					]
				},
				{
					"build" : "raylib/raylib/external/glfw/src",
					"jsonFile" : "directory-raylib.raylib.external.glfw.src-Release-4d55a53c058fdfa6d7b4.json",
					"minimumCMakeVersion" : 
					{
						"string" : "3.4"
					},
					"parentIndex" : 3,
					"projectIndex" : 2,
					"source" : "raylib/src/external/glfw/src",
					"targetIndexes" : 
					[
						5,
						7
					]
				}
			],
			"name" : "Release",
			"projects" : 
			[
				{
					"childIndexes" : 
					[
						1
					],
					"directoryIndexes" : 
					[
						0
					],
					"name" : "4MB_Game_Jam",
					"targetIndexes" : 
					[
						0,
						1,
						4
					]
				},
				{
					"childIndexes" : 
					[
						2
					],
					"directoryIndexes" : 
					[
						1,
						2
					],
					"name" : "raylib",
					"parentIndex" : 0,
					"targetIndexes" : 
					[
						2,
						6
					]
				},
				{
					"directoryIndexes" : 
					[
						3,
						4
					],
					"name" : "GLFW",
					"parentIndex" : 1,
					"targetIndexes" : 
					[
						3,
						5,
						7
					]
				}
			],
			"targets" : 
			[
				{
					"directoryIndex" : 0,
					"id" : "4MB_Game_Jam::@6890427a1f51a3e7e1df",
					"jsonFile" : "target-4MB_Game_Jam-Release-c8d992d59eb9c98f71e0.json",
					"name" : "4MB_Game_Jam",
					"projectIndex" : 0
				},
				{
					"directoryIndex" : 0,
					"id" : "ALL_BUILD::@6890427a1f51a3e7e1df",
					"jsonFile" : "target-ALL_BUILD-Release-2bcba8660bbe64b53a9c.json",
					"name" : "ALL_BUILD",
					"projectIndex" : 0
				},
				{
					"directoryIndex" : 1,
					"id" : "ALL_BUILD::@5003b8f497eeabc0006e",
					"jsonFile" : "target-ALL_BUILD-Release-c559b9ce9e9198be3419.json",
					"name" : "ALL_BUILD",
					"projectIndex" : 1
				},
				{
					"directoryIndex" : 3,
					"id" : "ALL_BUILD::@9b50ec0f4b893e94b571",
					"jsonFile" : "target-ALL_BUILD-Release-c98b6fdae7bb02c24a13.json",
					"name" : "ALL_BUILD",
					"projectIndex" : 2
				},
				{
					"directoryIndex" : 0,
					"id" : "ZERO_CHECK::@6890427a1f51a3e7e1df",
					"jsonFile" : "target-ZERO_CHECK-Release-85400f93d8e2ec8710c8.json",
					"name" : "ZERO_CHECK",
					"projectIndex" : 0
				},
				{
					"directoryIndex" : 4,
					"id" : "glfw::@a896dd99b4a5c6eab3d9",
					"jsonFile" : "target-glfw-Release-cb68b557fde5c190474b.json",
					"name" : "glfw",
					"projectIndex" : 2
				},
				{
					"directoryIndex" : 2,
					"id" : "raylib::@7d429ebd5d102775094d",
					"jsonFile" : "target-raylib-Release-980395b80db175b21333.json",
					"name" : "raylib",
					"projectIndex" : 1
				},
				{
					"directoryIndex" : 4,
					"id" : "update_mappings::@a896dd99b4a5c6eab3d9",
					"jsonFile" : "target-update_mappings-Release-b78b28e94bedbf65146e.json",
					"name" : "update_mappings",
					"projectIndex" : 2
				}
			]
		},
		{
			"directories" : 
			[
				{
					"build" : ".",
					"childIndexes" : 
					[
						1
					],
					"hasInstallRule" : true,
					"jsonFile" : "directory-.-MinSizeRel-d0094a50bb2071803777.json",
					"minimumCMakeVersion" : 
					{
						"string" : "3.10"
					},
					"projectIndex" : 0,
					"source" : ".",
					"targetIndexes" : 
					[
						0,
						1,
						4
					]
				},
				{
					"build" : "raylib",
					"childIndexes" : 
					[
						2
					],
					"hasInstallRule" : true,
					"jsonFile" : "directory-raylib-MinSizeRel-dac977eb2014d01c94e9.json",
					"minimumCMakeVersion" : 
					{
						"string" : "3.25"
					},
					"parentIndex" : 0,
					"projectIndex" : 1,
					"source" : "raylib",
					"targetIndexes" : 
					[
						2
					]
				},
				{
					"build" : "raylib/raylib",
					"childIndexes" : 
					[
						3
					],
					"hasInstallRule" : true,
					"jsonFile" : "directory-raylib.raylib-MinSizeRel-0b7ce25e17ff94f721ea.json",
					"minimumCMakeVersion" : 
					{
						"string" : "3.25"
					},
					"parentIndex" : 1,
					"projectIndex" : 1,
					"source" : "raylib/src",
					"targetIndexes" : 
					[
						6
					]
				},
				{
					"build" : "raylib/raylib/external/glfw",
					"childIndexes" : 
					[
						4
					],
					"jsonFile" : "directory-raylib.raylib.external.glfw-MinSizeRel-38845233cd217b380713.json",
					"minimumCMakeVersion" : 
					{
						"string" : "3.4"
					},
					"parentIndex" : 2,
					"projectIndex" : 2,
					"source" : "raylib/src/external/glfw",
					"targetIndexes" : 
					[
						3
					]
				},
				{
					"build" : "raylib/raylib/external/glfw/src",
					"jsonFile" : "directory-raylib.raylib.external.glfw.src-MinSizeRel-4d55a53c058fdfa6d7b4.json",
					"minimumCMakeVersion" : 
					{
						"string" : "3.4"
					},
					"parentIndex" : 3,
					"projectIndex" : 2,
					"source" : "raylib/src/external/glfw/src",
					"targetIndexes" : 
					[
						5,
						7
					]
				}
			],
			"name" : "MinSizeRel",
			"projects" : 
			[
				{
					"childIndexes" : 
					[
						1
					],
					"directoryIndexes" : 
					[
						0
					],
					"name" : "4MB_Game_Jam",
					"targetIndexes" : 
					[
						0,
						1,
						4
					]
				},
				{
					"childIndexes" : 
					[
						2
					],
					"directoryIndexes" : 
					[
						1,
						2
					],
					"name" : "raylib",
					"parentIndex" : 0,
					"targetIndexes" : 
					[
						2,
						6
					]
				},
				{
					"directoryIndexes" : 
					[
						3,
						4
					],
					"name" : "GLFW",
					"parentIndex" : 1,
					"targetIndexes" : 
					[
						3,
						5,
						7
					]
				}
			],
			"targets" : 
			[
				{
					"directoryIndex" : 0,
					"id" : "4MB_Game_Jam::@6890427a1f51a3e7e1df",
					"jsonFile" : "target-4MB_Game_Jam-MinSizeRel-6bdaf514f4d25e01b1c5.json",
					"name" : "4MB_Game_Jam",
					"projectIndex" : 0
				},
				{
					"directoryIndex" : 0,
					"id" : "ALL_BUILD::@6890427a1f51a3e7e1df",
					"jsonFile" : "target-ALL_BUILD-MinSizeRel-2bcba8660bbe64b53a9c.json",
					"name" : "ALL_BUILD",
					"projectIndex" : 0
				},
				{
					"directoryIndex" : 1,
					"id" : "ALL_BUILD::@5003b8f497eeabc0006e",
					"jsonFile" : "target-ALL_BUILD-MinSizeRel-c559b9ce9e9198be3419.json",
					"name" : "ALL_BUILD",
					"projectIndex" : 1
				},
				{
					"directoryIndex" : 3,
					"id" : "ALL_BUILD::@9b50ec0f4b893e94b571",
					"jsonFile" : "target-ALL_BUILD-MinSizeRel-c98b6fdae7bb02c24a13.json",
					"name" : "ALL_BUILD",
					"projectIndex" : 2
				},
				{
					"directoryIndex" : 0,
					"id" : "ZERO_CHECK::@6890427a1f51a3e7e1df",
					"jsonFile" : "target-ZERO_CHECK-MinSizeRel-85400f93d8e2ec8710c8.json",
					"name" : "ZERO_CHECK",
					"projectIndex" : 0
				},
				{
					"directoryIndex" : 4,
					"id" : "glfw::@a896dd99b4a5c6eab3d9",
					"jsonFile" : "target-glfw-MinSizeRel-b3e087748d2a9f355289.json",
					"name" : "glfw",
					"projectIndex" : 2
				},
				{
					"directoryIndex" : 2,
					"id" : "raylib::@7d429ebd5d102775094d",
					"jsonFile" : "target-raylib-MinSizeRel-ac3ac473e1fdc36df9a6.json",
					"name" : "raylib",
					"projectIndex" : 1
				},
				{
					"directoryIndex" : 4,
					"id" : "update_mappings::@a896dd99b4a5c6eab3d9",
					"jsonFile" : "target-update_mappings-MinSizeRel-b78b28e94bedbf65146e.json",
					"name" : "update_mappings",
					"projectIndex" : 2
				}
			]
		},
		{
			"directories" : 
			[
				{
					"build" : ".",
					"childIndexes" : 
					[
						1
					],
					"hasInstallRule" : true,
					"jsonFile" : "directory-.-RelWithDebInfo-d0094a50bb2071803777.json",
					"minimumCMakeVersion" : 
					{
						"string" : "3.10"
					},
					"projectIndex" : 0,
					"source" : ".",
					"targetIndexes" : 
					[
						0,
						1,
						4
					]
				},
				{
					"build" : "raylib",
					"childIndexes" : 
					[
						2
					],
					"hasInstallRule" : true,
					"jsonFile" : "directory-raylib-RelWithDebInfo-dac977eb2014d01c94e9.json",
					"minimumCMakeVersion" : 
					{
						"string" : "3.25"
					},
					"parentIndex" : 0,
					"projectIndex" : 1,
					"source" : "raylib",
					"targetIndexes" : 
					[
						2
					]
				},
				{
					"build" : "raylib/raylib",
					"childIndexes" : 
					[
						3
					],
					"hasInstallRule" : true,
					"jsonFile" : "directory-raylib.raylib-RelWithDebInfo-0120b03f20947bed3520.json",
					"minimumCMakeVersion" : 
					{
						"string" : "3.25"
					},
					"parentIndex" : 1,
					"projectIndex" : 1,
					"source" : "raylib/src",
					"targetIndexes" : 
					[
						6
					]
				},
				{
					"build" : "raylib/raylib/external/glfw",
					"childIndexes" : 
					[
						4
					],
					"jsonFile" : "directory-raylib.raylib.external.glfw-RelWithDebInfo-38845233cd217b380713.json",
					"minimumCMakeVersion" : 
					{
						"string" : "3.4"
					},
					"parentIndex" : 2,
					"projectIndex" : 2,
					"source" : "raylib/src/external/glfw",
					"targetIndexes" : 
					[
						3
					]
				},
				{
					"build" : "raylib/raylib/external/glfw/src",
					"jsonFile" : "directory-raylib.raylib.external.glfw.src-RelWithDebInfo-4d55a53c058fdfa6d7b4.json",
					"minimumCMakeVersion" : 
					{
						"string" : "3.4"
					},
					"parentIndex" : 3,
					"projectIndex" : 2,
					"source" : "raylib/src/external/glfw/src",
					"targetIndexes" : 
					[
						5,
						7
					]
				}
			],
			"name" : "RelWithDebInfo",
			"projects" : 
			[
				{
					"childIndexes" : 
					[
						1
					],
					"directoryIndexes" : 
					[
						0
					],
					"name" : "4MB_Game_Jam",
					"targetIndexes" : 
					[
						0,
						1,
						4
					]
				},
				{
					"childIndexes" : 
					[
						2
					],
					"directoryIndexes" : 
					[
						1,
						2
					],
					"name" : "raylib",
					"parentIndex" : 0,
					"targetIndexes" : 
					[
						2,
						6
					]
				},
				{
					"directoryIndexes" : 
					[
						3,
						4
					],
					"name" : "GLFW",
					"parentIndex" : 1,
					"targetIndexes" : 
					[
						3,
						5,
						7
					]
				}
			],
			"targets" : 
			[
				{
					"directoryIndex" : 0,
					"id" : "4MB_Game_Jam::@6890427a1f51a3e7e1df",
					"jsonFile" : "target-4MB_Game_Jam-RelWithDebInfo-ecf176bb8c7343291274.json",
					"name" : "4MB_Game_Jam",
					"projectIndex" : 0
				},
				{
					"directoryIndex" : 0,
					"id" : "ALL_BUILD::@6890427a1f51a3e7e1df",
					"jsonFile" : "target-ALL_BUILD-RelWithDebInfo-2bcba8660bbe64b53a9c.json",
					"name" : "ALL_BUILD",
					"projectIndex" : 0
				},
				{
					"directoryIndex" : 1,
					"id" : "ALL_BUILD::@5003b8f497eeabc0006e",
					"jsonFile" : "target-ALL_BUILD-RelWithDebInfo-c559b9ce9e9198be3419.json",
					"name" : "ALL_BUILD",
					"projectIndex" : 1
				},
				{
					"directoryIndex" : 3,
					"id" : "ALL_BUILD::@9b50ec0f4b893e94b571",
					"jsonFile" : "target-ALL_BUILD-RelWithDebInfo-c98b6fdae7bb02c24a13.json",
					"name" : "ALL_BUILD",
					"projectIndex" : 2
				},
				{
					"directoryIndex" : 0,
					"id" : "ZERO_CHECK::@6890427a1f51a3e7e1df",
					"jsonFile" : "target-ZERO_CHECK-RelWithDebInfo-85400f93d8e2ec8710c8.json",
					"name" : "ZERO_CHECK",
					"projectIndex" : 0
				},
				{
					"directoryIndex" : 4,
					"id" : "glfw::@a896dd99b4a5c6eab3d9",
					"jsonFile" : "target-glfw-RelWithDebInfo-9d18c6cff099f72a8133.json",
					"name" : "glfw",
					"projectIndex" : 2
				},
				{
					"directoryIndex" : 2,
					"id" : "raylib::@7d429ebd5d102775094d",
					"jsonFile" : "target-raylib-RelWithDebInfo-13a6c496fd52e36bce54.json",
					"name" : "raylib",
					"projectIndex" : 1
				},
				{
					"directoryIndex" : 4,
					"id" : "update_mappings::@a896dd99b4a5c6eab3d9",
					"jsonFile" : "target-update_mappings-RelWithDebInfo-b78b28e94bedbf65146e.json",
					"name" : "update_mappings",
					"projectIndex" : 2
				}
			]
		}
	],
	"kind" : "codemodel",
	"paths" : 
	{
		"build" : "C:/Users/Jon/Projects/Moros1138/4MB-Game-Jam-2025/build",
		"source" : "C:/Users/Jon/Projects/Moros1138/4MB-Game-Jam-2025"
	},
	"version" : 
	{
		"major" : 2,
		"minor" : 7
	}
}
